dsxquant/__init__.py
dsxquant/backtest/back_test.py
dsxquant/common/cache.py
dsxquant/common/fn.py
dsxquant/common/json2model.py
dsxquant/config/__init__.py
dsxquant/config/config.py
dsxquant/config/logconfig.py
dsxquant/dataser/__init__.py
dsxquant/dataser/dsx_dataser.py
dsxquant/dataser/models/quotes.py
dsxquant/dataser/models/result.py
dsxquant/dataser/parser/base.py
dsxquant/dataser/parser/get_category.py
dsxquant/dataser/parser/get_factors.py
dsxquant/dataser/parser/get_finance.py
dsxquant/dataser/parser/get_kline.py
dsxquant/dataser/parser/get_minkline.py
dsxquant/dataser/parser/get_quotes.py
dsxquant/dataser/parser/get_sharebonus.py
dsxquant/dataser/parser/get_stocks.py
dsxquant/dataser/parser/get_structure.py
dsxquant/dataser/parser/get_timesharing.py
dsxquant/dataser/parser/get_translist.py
dsxquant/dataser/parser/heart.py
dsxquant/dataser/parser/login.py
dsxquant/dataser/parser/register.py
dsxquant/dataser/parser/sub_all_quotes.py
dsxquant/emulation/base.py
dsxquant/emulation/buy.py
dsxquant/emulation/cancel.py
dsxquant/emulation/sell.py
dsxquant/engins/base.py
dsxquant/engins/cache_space.py
dsxquant/engins/data_feed.py
dsxquant/engins/emultion_engin.py
dsxquant/engins/engin.py
dsxquant/engins/event_bus.py
dsxquant/engins/event_model.py
dsxquant/engins/strategy_engin.py
dsxquant/engins/trade_engin.py
dsxquant/orders/orders.py
dsxquant/restful/__init__.py
dsxquant/restful/app.py
dsxquant/strategy/base.py
dsxquant/strategy/data_model.py
dsxquant/strategy/common/macross_strategy.py
dsxquant/strategy/common/myself_strategy.py
dsxquant/strategy/common/t_strategy.py
dsxquant/strategy/common/抛物线策略.py
dsxquant/strategy/common/放量突破策略.py
dsxquant/trade/base.py
dsxquant/trade/buy.py
dsxquant/trade/cancel.py
dsxquant/trade/sell.py
dsxquant-2.3.5.dist-info/LICENSE
dsxquant-2.3.5.dist-info/METADATA
dsxquant-2.3.5.dist-info/WHEEL
dsxquant-2.3.5.dist-info/top_level.txt
dsxquant-2.3.5.dist-info/RECORD
