Metadata-Version: 2.1
Name: dsxquant
Version: 2.3.5
Summary: Dsxquant 是一个基于python语言开发的的量化工具箱，主要特征是其工具属性，专为上层策略应用提供服务。
Home-page: https://github.com/dsxkline/dsxquant
Author: fangyunsm
Author-email: fangyunsm <934476300@qq.com>
License: MIT
Project-URL: Homepage, https://github.com/dsxkline/dsxquant
Project-URL: Bug Tracker, https://github.com/dsxkline/dsxquant/issues
Classifier: Programming Language :: Python :: 3
Classifier: License :: OSI Approved :: MIT License
Classifier: Operating System :: OS Independent
Requires-Python: >=3.6,<4
License-File: LICENSE
Requires-Dist: dsxindexer>=1.0.0
Requires-Dist: Flask==2.3.2
Requires-Dist: numpy==1.23.4
Requires-Dist: pandas==1.5.1
Requires-Dist: prettytable==3.7.0
Requires-Dist: progressbar33==2.4
Requires-Dist: Deprecated==1.2.13
